WebForms.py
wfc-2.0.0.dist-info/METADATA
wfc-2.0.0.dist-info/WHEEL
wfc-2.0.0.dist-info/top_level.txt
wfc-2.0.0.dist-info/RECORD
