Metadata-Version: 2.4
Name: WFC
Version: 2.0.0
Summary: The Back-End Part of WebForms Core Technology
Author-email: Elanat <info@elanat.net>
